[
  {
    "id": 1779241742938,
    "nome": "Felipe",
    "servico": "Corte de cabelo",
    "data": "2026-05-21",
    "horario": "08:00",
    "telefone": "48991500921",
    "criado_em": "2026-05-19T22:49:02.938807"
  },
  {
    "id": 1779241770659,
    "nome": "Gonzalez",
    "servico": "Corte + Barba",
    "data": "2026-05-21",
    "horario": "17:00",
    "telefone": "48991500921",
    "criado_em": "2026-05-19T22:49:30.659936"
  },
  {
    "id": 1779241785622,
    "nome": "Joao",
    "servico": "Corte + Barba",
    "data": "2026-05-21",
    "horario": "18:00",
    "telefone": "119247543546",
    "criado_em": "2026-05-19T22:49:45.622089"
  }
]